[
  {
    "title": "“인천홈플러스 폐점 반대” 구청장 5명 동참",
    "url": "https://www.kyeongin.com/article/1746293",
    "content": "홈플러스인천공동대책위원회(이하 대책위)는 16일 오전인천시청 앞에서 기자회견을 열고 “인천에서 홈플러스 점포가 있는남동구, 미추홀구, 연수구... 이어 “논현동주민만의 문제가 아니라 마트에 고용된인천지역 노동자, 지역상권에도 연쇄적으로 영향을 주는 문제인 만큼 동료 의원들을...",
    "summary": "홈플러스인천공동대책위원회(이하 대책위)는 16일 오전인천시청 앞에서 기자회견을 열고 “인천에서 홈플러스 점포가 있는남동구, 미추홀구, 연수구... 이어 “논현동주민만의 문제가 아니라 마트에 고용된인천지역 노동자, 지역상권에도 연쇄적으로 영향을 주는 문제인 만큼 동료 의원들을...",
    "press": "경인일보",
    "date": "2025-07-18",
    "crawled_at": "2025-07-18",
    "content_length": 156,
    "keyword": "인천 남동구 논현동",
    "section": "검색 결과",
    "type": "news"
  },
  {
    "title": "사무실 잠기고 지하차도 침수…인천서 비피해 24건",
    "url": "https://news.ifm.kr/news/articleView.html?idxno=447397",
    "content": "특히 오후 6시50분에는남동구 논현동한 사무실이 침수됐고, 서구 가정동에서는 상가 입구에 물이 들이쳐 이용객 발길이 묶이기도 했습니다. 불어난 빗물에남동구남촌농산물시장 인접 도로와인천대로에서 한때 배수 작업이 진행되기도 했습니다. 또, 퇴근시간 부평구 송내지하차도가 잠기는 아찔한...",
    "summary": "특히 오후 6시50분에는남동구 논현동한 사무실이 침수됐고, 서구 가정동에서는 상가 입구에 물이 들이쳐 이용객 발길이 묶이기도 했습니다. 불어난 빗물에남동구남촌농산물시장 인접 도로와인천대로에서 한때 배수 작업이 진행되기도 했습니다. 또, 퇴근시간 부평구 송내지하차도가 잠기는 아찔한...",
    "press": "경인방송",
    "date": "2025-07-18",
    "crawled_at": "2025-07-18",
    "content_length": 159,
    "keyword": "인천 남동구 논현동",
    "section": "검색 결과",
    "type": "news"
  },
  {
    "title": "불에 그을린지 1년 반…‘흉물’ 드디어 철거된다",
    "url": "https://www.kgnews.co.kr/news/article.html?no=854939",
    "content": "여겨지던남동구 논현동그랜드팰리스 호텔이 철거된다. 이곳에는 지난 2023년 12월 17일 대형 화재가 발생했다. 당시 불길이 치솟던 기계식 주차타워는... 부분이 있어 소유주 측에 이를 전달한 상황”이라고 설명했다. [ 경기신문 /인천= 이현도 기자 ] 화재로 제기능을 하지 못하는 호텔 그랜드펠리스. ( 사진 = )",
    "summary": "여겨지던남동구 논현동그랜드팰리스 호텔이 철거된다. 이곳에는 지난 2023년 12월 17일 대형 화재가 발생했다. 당시 불길이 치솟던 기계식 주차타워는... 부분이 있어 소유주 측에 이를 전달한 상황”이라고 설명했다. [ 경기신문 /인천= 이현도 기자 ] 화재로 제기능을 하지 못하는 호텔 그랜드펠리스. ( 사진 = )",
    "press": "경기신문",
    "date": "2025-07-18",
    "crawled_at": "2025-07-18",
    "content_length": 177,
    "keyword": "인천 남동구 논현동",
    "section": "검색 결과",
    "type": "news"
  },
  {
    "title": "[기자의 눈] 정쟁으로 막혀버린인천시 닥터헬기 계류장 이전",
    "url": "https://www.news1.kr/local/incheon/5843693",
    "content": "인천의 닥터헬기 계류장이 14년 만에 자리를 잡나 싶더니 정쟁에 가로막혔다. 때 되면 '하늘 위 응급실 닥터헬기 수천번 날아 수천 명을 살렸다'는... 이 땅은 승기천을 사이에 두고 400~500m 떨어진 곳에 연수구의 아파트 밀집 지역이 있고,남동구쪽으로도 1.5㎞ 떨어진 거리에 아파트 밀집 지역인논현동이 있다....",
    "summary": "인천의 닥터헬기 계류장이 14년 만에 자리를 잡나 싶더니 정쟁에 가로막혔다. 때 되면 '하늘 위 응급실 닥터헬기 수천번 날아 수천 명을 살렸다'는... 이 땅은 승기천을 사이에 두고 400~500m 떨어진 곳에 연수구의 아파트 밀집 지역이 있고,남동구쪽으로도 1.5㎞ 떨어진 거리에 아파트 밀집 지역인논현동이 있다....",
    "press": "뉴스1",
    "date": "2025-07-18",
    "crawled_at": "2025-07-18",
    "content_length": 179,
    "keyword": "인천 남동구 논현동",
    "section": "검색 결과",
    "type": "news"
  },
  {
    "title": "[대담한 인터뷰] 박종효, \"현장 목소리 '최우선'… 만수천 복원, 9월 중...",
    "url": "https://news.skbroadband.com/news/articleView.html?idxno=205880",
    "content": "이제논현택지개발, 서창지구택지개발, 그리고 과거 에는 재건축 사업이 남동구가 가장 활발하게 진행이 됐습니다. 그래서 한때 인구가 54만까지... 상인천재개발 구역하고 성락아파트 구역은 재개발이 진행되고 있는데 이곳에 3천 세대가 들어오면은 한 2만 3천 세대는 기본적으로… 일단 재개발이 예정지구가...",
    "summary": "이제논현택지개발, 서창지구택지개발, 그리고 과거 에는 재건축 사업이 남동구가 가장 활발하게 진행이 됐습니다. 그래서 한때 인구가 54만까지... 상인천재개발 구역하고 성락아파트 구역은 재개발이 진행되고 있는데 이곳에 3천 세대가 들어오면은 한 2만 3천 세대는 기본적으로… 일단 재개발이 예정지구가...",
    "press": "SK브로드밴드",
    "date": "2025-07-18",
    "crawled_at": "2025-07-18",
    "content_length": 169,
    "keyword": "인천 논현지구",
    "section": "검색 결과",
    "type": "news"
  },
  {
    "title": "인천남동구의회, 홈플러스 폐점·매각 반대 결의안 채택",
    "url": "https://www.newscj.com/news/articleView.html?idxno=3293591",
    "content": "인천남동구의회가 지역 내 대형마트인 홈플러스의 폐점 및 매각 움직임에 대해 강력한 우려를 표명하며, 지방정부와 정치권 차원의 적극적 대응을 촉구하고 나섰다. 남동구의회는 15일 제305회 임시회 본회의에서 이철상 의원(더불어민주당,논현1·2동,논현고잔동)이 대표 발의한 '홈플러스 폐점·매각에 따른...",
    "summary": "인천남동구의회가 지역 내 대형마트인 홈플러스의 폐점 및 매각 움직임에 대해 강력한 우려를 표명하며, 지방정부와 정치권 차원의 적극적 대응을 촉구하고 나섰다. 남동구의회는 15일 제305회 임시회 본회의에서 이철상 의원(더불어민주당,논현1·2동,논현고잔동)이 대표 발의한 '홈플러스 폐점·매각에 따른...",
    "press": "천지일보",
    "date": "2025-07-18",
    "crawled_at": "2025-07-18",
    "content_length": 169,
    "keyword": "인천 논현고잔동",
    "section": "검색 결과",
    "type": "news"
  },
  {
    "title": "인천남동구의회 '홈플러스 폐점·매각에 따른 지역경제 붕괴 우려 및 대...",
    "url": "http://www.m-i.kr/news/articleView.html?idxno=1260263",
    "content": "최근인천내 주요 생활 인프라 시설이 잇따라 폐점·매각 위기에 처하면서 지방정부 및 정치권의 행동 촉구가 요구되는 가운데 남동구의회가 15일 제305회 임시회 본회의에서 이철상 의원(논현1,논현2,논현고잔동/더불어민주당)이 발의한 '홈플러스 폐점·매각에 따른 지역경제 붕괴 우려 및 대응 촉구 결의안'을...",
    "summary": "최근인천내 주요 생활 인프라 시설이 잇따라 폐점·매각 위기에 처하면서 지방정부 및 정치권의 행동 촉구가 요구되는 가운데 남동구의회가 15일 제305회 임시회 본회의에서 이철상 의원(논현1,논현2,논현고잔동/더불어민주당)이 발의한 '홈플러스 폐점·매각에 따른 지역경제 붕괴 우려 및 대응 촉구 결의안'을...",
    "press": "매일일보",
    "date": "2025-07-18",
    "crawled_at": "2025-07-18",
    "content_length": 171,
    "keyword": "인천 논현고잔동",
    "section": "검색 결과",
    "type": "news"
  },
  {
    "title": "[포토] 수위 높아진소래포구",
    "url": "https://www.incheonilbo.com/news/articleView.html?idxno=1296415",
    "content": "▲ 조수 간만의 차가 가장 큰 대조기 기간인 16일 인천 남동구소래포구일대 밀물 수위가 높아져 있다. /이재민 기자 leejm@incheonilbo.com",
    "summary": "▲ 조수 간만의 차가 가장 큰 대조기 기간인 16일 인천 남동구소래포구일대 밀물 수위가 높아져 있다. /이재민 기자 leejm@incheonilbo.com",
    "press": "인천일보",
    "date": "2025-07-18",
    "crawled_at": "2025-07-18",
    "content_length": 86,
    "keyword": "소래포구",
    "section": "검색 결과",
    "type": "news"
  },
  {
    "title": "소래포구·구월·모래내시장... 환승 투어 매력 발산",
    "url": "https://www.gukjenews.com/news/articleView.html?idxno=3323910",
    "content": "인천국제공항을 방문한 외국인 관광객을 대상으로 운영하는 남동구소래포구‧구월‧모래내시장 환승 투어 프로그램이 큰 호응을 얻고 있다. 사진=남동구 인천국제공항을 방문한 외국인 관광객을 대상으로 운영하는 남동구 환승 투어 프로그램이 큰 호응을 얻고 있다. 남동구는 지난해 12월부터 현재까지 총...",
    "summary": "인천국제공항을 방문한 외국인 관광객을 대상으로 운영하는 남동구소래포구‧구월‧모래내시장 환승 투어 프로그램이 큰 호응을 얻고 있다. 사진=남동구 인천국제공항을 방문한 외국인 관광객을 대상으로 운영하는 남동구 환승 투어 프로그램이 큰 호응을 얻고 있다. 남동구는 지난해 12월부터 현재까지 총...",
    "press": "국제뉴스",
    "date": "2025-07-18",
    "crawled_at": "2025-07-18",
    "content_length": 164,
    "keyword": "소래포구",
    "section": "검색 결과",
    "type": "news"
  },
  {
    "title": "\"스탬프 찍고 할인 받자\"…인천시, 전통시장 모바일 스탬프투어 실시",
    "url": "https://www.factin.co.kr/news/articleView.html?idxno=4635",
    "content": "참여 시장은 신흥시장, 석바위시장, 인천모래내시장,소래포구전통어시장, 강화풍물시장, 신포국제시장, 계산시장 등 인천 전역에 걸쳐 있으며, 참가자들은 '인천e지' 앱을 통해 총 15개 코스 중 원하는 코스를 선택해 전통시장과 주변 관광지를 방문하며 스탬프를 모으면 된다. 코스를 완주할 때마다 5천 원...",
    "summary": "참여 시장은 신흥시장, 석바위시장, 인천모래내시장,소래포구전통어시장, 강화풍물시장, 신포국제시장, 계산시장 등 인천 전역에 걸쳐 있으며, 참가자들은 '인천e지' 앱을 통해 총 15개 코스 중 원하는 코스를 선택해 전통시장과 주변 관광지를 방문하며 스탬프를 모으면 된다. 코스를 완주할 때마다 5천 원...",
    "press": "여론과뉴스",
    "date": "2025-07-18",
    "crawled_at": "2025-07-18",
    "content_length": 170,
    "keyword": "소래포구",
    "section": "검색 결과",
    "type": "news"
  },
  {
    "title": "인천시 남동구, ‘인천공항 환승 투어’외국인 관광객에 큰 호응",
    "url": "https://www.siminilbo.co.kr/news/newsview.php?ncode=1160282832954172",
    "content": "소래포구와 구월‧모래내시장 환승 투어로 K-컬처 매력 발산 다양한 관광․체험 프로그램 개발 통해 지역경제 및 관광 활성화 추진 인천국제공항을 방문한 외국인 관광객을 대상으로 운영하는 남동구 환승 투어 프로그램이 참가자들의 높은 호응을 얻고 있다. 남동구는 지난해 12월부터 현재까지 총 54차례의...",
    "summary": "소래포구와 구월‧모래내시장 환승 투어로 K-컬처 매력 발산 다양한 관광․체험 프로그램 개발 통해 지역경제 및 관광 활성화 추진 인천국제공항을 방문한 외국인 관광객을 대상으로 운영하는 남동구 환승 투어 프로그램이 참가자들의 높은 호응을 얻고 있다. 남동구는 지난해 12월부터 현재까지 총 54차례의...",
    "press": "시민일보",
    "date": "2025-07-18",
    "crawled_at": "2025-07-18",
    "content_length": 168,
    "keyword": "소래포구",
    "section": "검색 결과",
    "type": "news"
  },
  {
    "title": "[창간 37]인천형 광역교통망의 미래는",
    "url": "http://www.kihoilbo.co.kr/news/articleView.html?idxno=1152293",
    "content": "이와 함께 제2차 도시철도망 계획에 반영된 노선은 ▶용현서창선 ▶송도트램 ▶부평연안부두선 ▶인천2호선논현연장 ▶영종트램 ▶가좌송도선 등 총 7개 노선이다. 장래 여건 변화에 따라 우선 검토될 후보 노선으로는 주안연수선과 자기부상열차 장래 확장 등 2개 노선이 제시됐다. # 해묵은 교통현안...",
    "summary": "이와 함께 제2차 도시철도망 계획에 반영된 노선은 ▶용현서창선 ▶송도트램 ▶부평연안부두선 ▶인천2호선논현연장 ▶영종트램 ▶가좌송도선 등 총 7개 노선이다. 장래 여건 변화에 따라 우선 검토될 후보 노선으로는 주안연수선과 자기부상열차 장래 확장 등 2개 노선이 제시됐다. # 해묵은 교통현안...",
    "press": "기호일보",
    "date": "2025-07-18",
    "crawled_at": "2025-07-18",
    "content_length": 164,
    "keyword": "인천논현",
    "section": "검색 결과",
    "type": "news"
  },
  {
    "title": "[경찰] 안영진인천논현경찰서 순찰요원",
    "url": "http://www.kihoilbo.co.kr/news/articleView.html?idxno=1152407",
    "content": "저는논현경찰서에서 순찰요원으로 근무하면서 매일같이 지역 곳곳을 다니고 있습니다. 특별히 큰일을 한 것도 아니고 그저 당연한 일을 했다고 생각했는데 그 노력을 알아봐 주셔서 더없이 감사할 따름입니다. 현장에서 묵묵히 일하는 많은 동료 경찰관들을 대신해 받은 상이라 생각하며 무거운 책임감도...",
    "summary": "저는논현경찰서에서 순찰요원으로 근무하면서 매일같이 지역 곳곳을 다니고 있습니다. 특별히 큰일을 한 것도 아니고 그저 당연한 일을 했다고 생각했는데 그 노력을 알아봐 주셔서 더없이 감사할 따름입니다. 현장에서 묵묵히 일하는 많은 동료 경찰관들을 대신해 받은 상이라 생각하며 무거운 책임감도...",
    "press": "기호일보",
    "date": "2025-07-18",
    "crawled_at": "2025-07-18",
    "content_length": 163,
    "keyword": "인천논현",
    "section": "검색 결과",
    "type": "news"
  }
]